officeparserpy/__init__.py
officeparserpy/officeparserpy.py
officeparserpy-1.0.9.dist-info/LICENSE
officeparserpy-1.0.9.dist-info/METADATA
officeparserpy-1.0.9.dist-info/WHEEL
officeparserpy-1.0.9.dist-info/entry_points.txt
officeparserpy-1.0.9.dist-info/top_level.txt
officeparserpy-1.0.9.dist-info/RECORD
