Metadata-Version: 2.1
Name: officeparserpy
Version: 1.0.9
Summary: A Python library to parse text out of any office file. Currently supports docx, pptx, xlsx, odt, odp, ods, pdf files.
Home-page: https://github.com/harshankur/officeparserpy
Author: Harsh Ankur
Author-email: harshankur@outlook.com
Classifier: Programming Language :: Python :: 3
Classifier: License :: OSI Approved :: MIT License
Classifier: Operating System :: OS Independent
License-File: LICENSE
Requires-Dist: typing-extensions
Requires-Dist: filetype
Requires-Dist: pdfminer.six
